Workbook

Sheet Inventory Master
A1: Stone ID | B1: Shape | C1: Carat | D1: Color | E1: Clarity | F1: Cut | G1: Polish | H1: Symmetry | I1: Fluorescence | J1: Lab | K1: Certificate No | L1: Measurements | M1: Rap Price | N1: Discount % | O1: Cost Price | P1: Selling Price | Q1: Supplier | R1: Location | S1: Status | T1: Date Purchased | U1: Date Sold | V1: Customer
A2: ST001 | B2: Round | C2: 1.2 | D2: D | E2: VVS1 | F2: Excellent | G2: Excellent | H2: Excellent | I2: None | J2: GIA | K2: GIA123456 | L2: 6.8x6.8x4.2 | M2: 8000 | N2: 20 | O2: 6000 | P2: 7500 | Q2: Star Diamonds | R2: Mumbai | S2: Available | T2: 46054

Sheet Purchase Entry
A1: Date | B1: Supplier | C1: Invoice No | D1: Stone ID | E1: Carat | F1: Cost Price | G1: Total Amount | H1: Currency | I1: Payment Status | J1: Due Date
A2: 46054 | B2: Star Diamonds | C2: INV-1001 | D2: ST001 | E2: 1.2 | F2: 5000 | G2: =E2*F2 -> 6000 | H2: USD | I2: Unpaid | J2: 46068
G3: =E3*F3 -> 0
G4: =E4*F4 -> 0
G5: =E5*F5 -> 0
G6: =E6*F6 -> 0
G7: =E7*F7 -> 0
G8: =E8*F8 -> 0
G9: =E9*F9 -> 0
G10: =E10*F10 -> 0
G11: =E11*F11 -> 0
G12: =E12*F12 -> 0
G13: =E13*F13 -> 0
G14: =E14*F14 -> 0
... G999: =E999*F999 -> 0

Sheet Sales Entry
A1: Date | B1: Customer | C1: Invoice No | D1: Stone ID | E1: Carat | F1: Selling Price | G1: Total Amount | H1: Currency | I1: Payment Status | J1: Due Date | K1: Cost Price (Lookup) | L1: Profit
A2: 46058 | B2: Royal Jewels | C2: SAL-2001 | D2: ST001 | E2: 1.2 | F2: 7500 | G2: =E2*F2 -> 9000 | H2: USD | I2: Unpaid | J2: 46073 | K2: =IFERROR(VLOOKUP(D2,'Inventory Master'!A:P,15,FALSE),0) -> 6000 | L2: =G2-K2 -> 3000
G3: =E3*F3 -> 0 | K3: =IFERROR(VLOOKUP(D3,'Inventory Master'!A:P,15,FALSE),0) -> 0 | L3: =G3-K3 -> 0
G4: =E4*F4 -> 0 | K4: =IFERROR(VLOOKUP(D4,'Inventory Master'!A:P,15,FALSE),0) -> 0 | L4: =G4-K4 -> 0
G5: =E5*F5 -> 0 | K5: =IFERROR(VLOOKUP(D5,'Inventory Master'!A:P,15,FALSE),0) -> 0 | L5: =G5-K5 -> 0
G6: =E6*F6 -> 0 | K6: =IFERROR(VLOOKUP(D6,'Inventory Master'!A:P,15,FALSE),0) -> 0 | L6: =G6-K6 -> 0
G7: =E7*F7 -> 0 | K7: =IFERROR(VLOOKUP(D7,'Inventory Master'!A:P,15,FALSE),0) -> 0 | L7: =G7-K7 -> 0
G8: =E8*F8 -> 0 | K8: =IFERROR(VLOOKUP(D8,'Inventory Master'!A:P,15,FALSE),0) -> 0 | L8: =G8-K8 -> 0
G9: =E9*F9 -> 0 | K9: =IFERROR(VLOOKUP(D9,'Inventory Master'!A:P,15,FALSE),0) -> 0 | L9: =G9-K9 -> 0
G10: =E10*F10 -> 0 | K10: =IFERROR(VLOOKUP(D10,'Inventory Master'!A:P,15,FALSE),0) -> 0 | L10: =G10-K10 -> 0
G11: =E11*F11 -> 0 | K11: =IFERROR(VLOOKUP(D11,'Inventory Master'!A:P,15,FALSE),0) -> 0 | L11: =G11-K11 -> 0
G12: =E12*F12 -> 0 | K12: =IFERROR(VLOOKUP(D12,'Inventory Master'!A:P,15,FALSE),0) -> 0 | L12: =G12-K12 -> 0
G13: =E13*F13 -> 0 | K13: =IFERROR(VLOOKUP(D13,'Inventory Master'!A:P,15,FALSE),0) -> 0 | L13: =G13-K13 -> 0
G14: =E14*F14 -> 0 | K14: =IFERROR(VLOOKUP(D14,'Inventory Master'!A:P,15,FALSE),0) -> 0 | L14: =G14-K14 -> 0
... G999: =E999*F999 -> 0 | K999: =IFERROR(VLOOKUP(D999,'Inventory Master'!A:P,15,FALSE),0) -> 0 | L999: =G999-K999 -> 0

Sheet Payments Received
A1: Date | B1: Customer | C1: Amount | D1: Invoice Ref | E1: Currency | F1: Mode | G1: Notes
A2: 46063 | B2: Royal Jewels | C2: 9000 | D2: SAL-2001 | E2: USD | F2: Bank | G2: Full Payment

Sheet Payments Made
A1: Date | B1: Supplier | C1: Amount | D1: Invoice Ref | E1: Currency | F1: Mode | G1: Notes

Sheet Expenses
A1: Date | B1: Category | C1: Description | D1: Amount | E1: Currency
A2: 46059 | B2: Office Rent | C2: February Rent | D2: 500 | E2: USD

Sheet Dashboard
A1: Diamond Trading ERP Dashboard
A3: Total Sales | B3: =SUM('Sales Entry'!G:G) -> 9000
A4: Total Purchases | B4: =SUM('Purchase Entry'!G:G) -> 6000
A5: Total Profit | B5: =SUM('Sales Entry'!L:L) -> 3000
A6: Total Expenses | B6: =SUM(Expenses!D:D) -> 500
A7: Net Profit | B7: =B5-B6 -> 2500

Sheet P&L Report
A1: Monthly P&L Summary
A3: Total Sales | B3: =SUM('Sales Entry'!G:G) -> 9000
A4: COGS | B4: =SUM('Sales Entry'!K:K) -> 6000
A5: Gross Profit | B5: =B3-B4 -> 3000
A6: Expenses | B6: =SUM(Expenses!D:D) -> 500
A7: Net Profit | B7: =B5-B6 -> 2500
