Workbook

Sheet Customers
A1: Customer Name | B1: Country | C1: Credit Limit (USD) | D1: Outstanding (Auto) | E1: Credit Alert
D2: =SUMIF('Sales Entry'!B:B,A2,'Sales Entry'!H:H)-SUMIF('Payments Received'!B:B,A2,'Payments Received'!C:C) -> 0 | E2: =IF(D2>C2,"OVER LIMIT","OK") -> OK
D3: =SUMIF('Sales Entry'!B:B,A3,'Sales Entry'!H:H)-SUMIF('Payments Received'!B:B,A3,'Payments Received'!C:C) -> 0 | E3: =IF(D3>C3,"OVER LIMIT","OK") -> OK
D4: =SUMIF('Sales Entry'!B:B,A4,'Sales Entry'!H:H)-SUMIF('Payments Received'!B:B,A4,'Payments Received'!C:C) -> 0 | E4: =IF(D4>C4,"OVER LIMIT","OK") -> OK
D5: =SUMIF('Sales Entry'!B:B,A5,'Sales Entry'!H:H)-SUMIF('Payments Received'!B:B,A5,'Payments Received'!C:C) -> 0 | E5: =IF(D5>C5,"OVER LIMIT","OK") -> OK
D6: =SUMIF('Sales Entry'!B:B,A6,'Sales Entry'!H:H)-SUMIF('Payments Received'!B:B,A6,'Payments Received'!C:C) -> 0 | E6: =IF(D6>C6,"OVER LIMIT","OK") -> OK
D7: =SUMIF('Sales Entry'!B:B,A7,'Sales Entry'!H:H)-SUMIF('Payments Received'!B:B,A7,'Payments Received'!C:C) -> 0 | E7: =IF(D7>C7,"OVER LIMIT","OK") -> OK
D8: =SUMIF('Sales Entry'!B:B,A8,'Sales Entry'!H:H)-SUMIF('Payments Received'!B:B,A8,'Payments Received'!C:C) -> 0 | E8: =IF(D8>C8,"OVER LIMIT","OK") -> OK
D9: =SUMIF('Sales Entry'!B:B,A9,'Sales Entry'!H:H)-SUMIF('Payments Received'!B:B,A9,'Payments Received'!C:C) -> 0 | E9: =IF(D9>C9,"OVER LIMIT","OK") -> OK
D10: =SUMIF('Sales Entry'!B:B,A10,'Sales Entry'!H:H)-SUMIF('Payments Received'!B:B,A10,'Payments Received'!C:C) -> 0 | E10: =IF(D10>C10,"OVER LIMIT","OK") -> OK
D11: =SUMIF('Sales Entry'!B:B,A11,'Sales Entry'!H:H)-SUMIF('Payments Received'!B:B,A11,'Payments Received'!C:C) -> 0 | E11: =IF(D11>C11,"OVER LIMIT","OK") -> OK
D12: =SUMIF('Sales Entry'!B:B,A12,'Sales Entry'!H:H)-SUMIF('Payments Received'!B:B,A12,'Payments Received'!C:C) -> 0 | E12: =IF(D12>C12,"OVER LIMIT","OK") -> OK
D13: =SUMIF('Sales Entry'!B:B,A13,'Sales Entry'!H:H)-SUMIF('Payments Received'!B:B,A13,'Payments Received'!C:C) -> 0 | E13: =IF(D13>C13,"OVER LIMIT","OK") -> OK
... D499: =SUMIF('Sales Entry'!B:B,A499,'Sales Entry'!H:H)-SUMIF('Payments Received'!B:B,A499,'Payments Received'!C:C) -> 0 | E499: =IF(D499>C499,"OVER LIMIT","OK") -> OK

Sheet Suppliers
A1: Supplier Name | B1: Country

Sheet FX Rates
A1: Currency | B1: Rate to USD
A2: USD | B2: 1
A3: INR | B3: 0.012
A4: VND | B4: 4.1e-05

Sheet Inventory Master
A1: Stone ID | B1: Carat | C1: Cost USD | D1: Selling USD | E1: Status (Auto)
E2: =IF(COUNTIF('Sales Entry'!D:D,A2)>0,"Sold","Available") -> Available
E3: =IF(COUNTIF('Sales Entry'!D:D,A3)>0,"Sold","Available") -> Available
E4: =IF(COUNTIF('Sales Entry'!D:D,A4)>0,"Sold","Available") -> Available
E5: =IF(COUNTIF('Sales Entry'!D:D,A5)>0,"Sold","Available") -> Available
E6: =IF(COUNTIF('Sales Entry'!D:D,A6)>0,"Sold","Available") -> Available
E7: =IF(COUNTIF('Sales Entry'!D:D,A7)>0,"Sold","Available") -> Available
E8: =IF(COUNTIF('Sales Entry'!D:D,A8)>0,"Sold","Available") -> Available
E9: =IF(COUNTIF('Sales Entry'!D:D,A9)>0,"Sold","Available") -> Available
E10: =IF(COUNTIF('Sales Entry'!D:D,A10)>0,"Sold","Available") -> Available
E11: =IF(COUNTIF('Sales Entry'!D:D,A11)>0,"Sold","Available") -> Available
E12: =IF(COUNTIF('Sales Entry'!D:D,A12)>0,"Sold","Available") -> Available
E13: =IF(COUNTIF('Sales Entry'!D:D,A13)>0,"Sold","Available") -> Available
... E999: =IF(COUNTIF('Sales Entry'!D:D,A999)>0,"Sold","Available") -> Available

Sheet Purchase Entry
A1: Date | B1: Supplier | C1: Stone ID | D1: Carat | E1: Cost | F1: Currency | G1: Cost USD | H1: Due Date
G2: =E2*VLOOKUP(F2,'FX Rates'!A:B,2,FALSE) -> #N/A
G3: =E3*VLOOKUP(F3,'FX Rates'!A:B,2,FALSE) -> #N/A
G4: =E4*VLOOKUP(F4,'FX Rates'!A:B,2,FALSE) -> #N/A
G5: =E5*VLOOKUP(F5,'FX Rates'!A:B,2,FALSE) -> #N/A
G6: =E6*VLOOKUP(F6,'FX Rates'!A:B,2,FALSE) -> #N/A
G7: =E7*VLOOKUP(F7,'FX Rates'!A:B,2,FALSE) -> #N/A
G8: =E8*VLOOKUP(F8,'FX Rates'!A:B,2,FALSE) -> #N/A
G9: =E9*VLOOKUP(F9,'FX Rates'!A:B,2,FALSE) -> #N/A
G10: =E10*VLOOKUP(F10,'FX Rates'!A:B,2,FALSE) -> #N/A
G11: =E11*VLOOKUP(F11,'FX Rates'!A:B,2,FALSE) -> #N/A
G12: =E12*VLOOKUP(F12,'FX Rates'!A:B,2,FALSE) -> #N/A
G13: =E13*VLOOKUP(F13,'FX Rates'!A:B,2,FALSE) -> #N/A
... G999: =E999*VLOOKUP(F999,'FX Rates'!A:B,2,FALSE) -> #N/A

Sheet Sales Entry
A1: Date | B1: Customer | C1: Invoice No | D1: Stone ID | E1: Carat | F1: Price | G1: Currency | H1: Total USD | I1: Due Date | J1: Aging Days
H2: =F2*E2*VLOOKUP(G2,'FX Rates'!A:B,2,FALSE) -> #N/A | J2: =IF(I2="",0,TODAY()-I2) -> 0
H3: =F3*E3*VLOOKUP(G3,'FX Rates'!A:B,2,FALSE) -> #N/A | J3: =IF(I3="",0,TODAY()-I3) -> 0
H4: =F4*E4*VLOOKUP(G4,'FX Rates'!A:B,2,FALSE) -> #N/A | J4: =IF(I4="",0,TODAY()-I4) -> 0
H5: =F5*E5*VLOOKUP(G5,'FX Rates'!A:B,2,FALSE) -> #N/A | J5: =IF(I5="",0,TODAY()-I5) -> 0
H6: =F6*E6*VLOOKUP(G6,'FX Rates'!A:B,2,FALSE) -> #N/A | J6: =IF(I6="",0,TODAY()-I6) -> 0
H7: =F7*E7*VLOOKUP(G7,'FX Rates'!A:B,2,FALSE) -> #N/A | J7: =IF(I7="",0,TODAY()-I7) -> 0
H8: =F8*E8*VLOOKUP(G8,'FX Rates'!A:B,2,FALSE) -> #N/A | J8: =IF(I8="",0,TODAY()-I8) -> 0
H9: =F9*E9*VLOOKUP(G9,'FX Rates'!A:B,2,FALSE) -> #N/A | J9: =IF(I9="",0,TODAY()-I9) -> 0
H10: =F10*E10*VLOOKUP(G10,'FX Rates'!A:B,2,FALSE) -> #N/A | J10: =IF(I10="",0,TODAY()-I10) -> 0
H11: =F11*E11*VLOOKUP(G11,'FX Rates'!A:B,2,FALSE) -> #N/A | J11: =IF(I11="",0,TODAY()-I11) -> 0
H12: =F12*E12*VLOOKUP(G12,'FX Rates'!A:B,2,FALSE) -> #N/A | J12: =IF(I12="",0,TODAY()-I12) -> 0
H13: =F13*E13*VLOOKUP(G13,'FX Rates'!A:B,2,FALSE) -> #N/A | J13: =IF(I13="",0,TODAY()-I13) -> 0
... H999: =F999*E999*VLOOKUP(G999,'FX Rates'!A:B,2,FALSE) -> #N/A | J999: =IF(I999="",0,TODAY()-I999) -> 0

Sheet Receivable Aging
A1: Invoice | B1: Customer | C1: Due Date | D1: Amount USD | E1: Aging Bucket

Sheet Payable Aging
A1: Supplier | B1: Due Date | C1: Amount USD | D1: Aging Days
D2: =IF(B2="",0,TODAY()-B2) -> 0
D3: =IF(B3="",0,TODAY()-B3) -> 0
D4: =IF(B4="",0,TODAY()-B4) -> 0
D5: =IF(B5="",0,TODAY()-B5) -> 0
D6: =IF(B6="",0,TODAY()-B6) -> 0
D7: =IF(B7="",0,TODAY()-B7) -> 0
D8: =IF(B8="",0,TODAY()-B8) -> 0
D9: =IF(B9="",0,TODAY()-B9) -> 0
D10: =IF(B10="",0,TODAY()-B10) -> 0
D11: =IF(B11="",0,TODAY()-B11) -> 0
D12: =IF(B12="",0,TODAY()-B12) -> 0
D13: =IF(B13="",0,TODAY()-B13) -> 0
... D499: =IF(B499="",0,TODAY()-B499) -> 0

Sheet Payments Received
A1: Date | B1: Customer | C1: Amount | D1: Invoice Ref

Sheet Payments Made
A1: Date | B1: Supplier | C1: Amount | D1: Invoice Ref

Sheet Invoice Template
A1: INVOICE
A3: Customer:
A4: Invoice No:
A5: Date:
A7: Stone ID | B7: Carat | C7: Price | D7: Total
C10: Grand Total USD | D10: =SUM(D8:D20)

Sheet Dashboard
A1: Executive Dashboard
A3: Total Sales USD | B3: =SUM('Sales Entry'!H:H) -> #N/A
A4: Total Purchases USD | B4: =SUM('Purchase Entry'!G:G) -> #N/A
A5: Total Receivable | B5: =SUM(Customers!D:D) -> 0
A6: Total Payable | B6: =SUM('Purchase Entry'!G:G)-SUM('Payments Made'!C:C) -> #N/A
A7: Net Profit | B7: =B3-B4 -> #N/A
